windowsxpllll/__init__.py
windowsxpllll/projects/__init__.py
windowsxpllll/projects/config.py
windowsxpllll/projects/config_new.py
windowsxpllll/projects/dimension_reduction.py
windowsxpllll/projects/main_stand.py
windowsxpllll/projects/predict.py
windowsxpllll/root/TimeSeriesFactor.py
windowsxpllll/root/__init__.py
windowsxpllll/root/model_automl_with_auto_dt.py
windowsxpllll/root/readme.py
windowsxpllll/root/requirements.py
windowsxpllll/src/__init__.py
windowsxpllll/src/cat_search_space.py
windowsxpllll/src/config.py
windowsxpllll/src/evaluation.py
windowsxpllll/src/feature_engineering.py
windowsxpllll/src/feature_processor.py
windowsxpllll/src/lgb_search_space.py
windowsxpllll/src/model_automl.py
windowsxpllll/src/model_ensemble.py
windowsxpllll/src/model_stacking.py
windowsxpllll/src/model_tuning.py
windowsxpllll/src/xgb_search_space.py
windowsxpllll-0.1.0.dist-info/METADATA
windowsxpllll-0.1.0.dist-info/WHEEL
windowsxpllll-0.1.0.dist-info/entry_points.txt
windowsxpllll-0.1.0.dist-info/top_level.txt
windowsxpllll-0.1.0.dist-info/RECORD
